lazy_db/__init__.py
lazy_db/lazy_db.py
lazy_database-1.1.0.dist-info/LICENSE
lazy_database-1.1.0.dist-info/METADATA
lazy_database-1.1.0.dist-info/WHEEL
lazy_database-1.1.0.dist-info/top_level.txt
lazy_database-1.1.0.dist-info/RECORD
