Metadata-Version: 2.1
Name: lazy-database
Version: 1.1.0
Summary: A simple lazy loaded key:value database
Home-page: https://github.com/Themis3000/lazy_db
Author: Themi Megas
Author-email: tcm4760@gmail.com
License: MIT license
Keywords: lazy_db
Platform: UNKNOWN
Classifier: Development Status :: 2 - Pre-Alpha
Classifier: Intended Audience :: Developers
Classifier: License :: OSI Approved :: MIT License
Classifier: Natural Language :: English
Classifier: Programming Language :: Python :: 3
Classifier: Programming Language :: Python :: 3.8
Classifier: Programming Language :: Python :: 3.9
Classifier: Programming Language :: Python :: 3.10
Requires-Python: >=3.8
License-File: LICENSE
